{"q1": {"RoomName": "Quarto 1", "Item": {"Q1_001": {"Name": "Criado-mudo", "Quantity": "2", "Height": 70, "Width": 40, "Depth": 30, "PictureMin": 1, "PictureMax": 2, "Damage": "Pequenos riscos", "Action": "Reservado", "Price": 350}, "Q1_002": {"Name": "Tapete de carneiro", "Quantity": 1, "Height": 1, "Width": 80, "Depth": 125, "PictureMin": 1, "PictureMax": 1, "Damage": "Rasgado na metade", "Action": "Dispon\u00edvel", "Price": 0}, "Q1_003": {"Name": "Cabide", "Quantity": 100, "Height": 24, "Width": 44, "Depth": 1, "PictureMin": 1, "PictureMax": 1, "Damage": "-", "Action": "Dispon\u00edvel", "Price": 25}, "Q1_004": {"Name": "Abajur", "Quantity": 1, "Height": 32, "Width": 12, "Depth": 12, "PictureMin": 1, "PictureMax": 1, "Damage": "Lateral manchada", "Action": "Dispon\u00edvel", "Price": 0}, "Q1_007": {"Name": "Bolsa de amamenta\u00e7\u00e3o", "Quantity": "2", "Height": 25, "Width": 42, "Depth": 20, "PictureMin": 1, "PictureMax": 1, "Damage": "-", "Action": "Dispon\u00edvel", "Price": 25}, "Q1_009": {"Name": "Colcha", "Quantity": "3", "Height": 280, "Width": 235, "Depth": 1, "PictureMin": 1, "PictureMax": 1, "Damage": "-", "Action": "Dispon\u00edvel", "Price": 25}, "Q1_010": {"Name": "Roup\u00e3o", "Quantity": "2", "Height": 130, "Width": 45, "Depth": 10, "PictureMin": 1, "PictureMax": 4, "Damage": "-", "Action": "Dispon\u00edvel", "Price": 50}, "Q1_011_A": {"Name": "Cal\u00e7a de gr\u00e1vida", "Quantity": 1, "Height": 120, "Width": "40", "Depth": 5, "PictureMin": 1, "PictureMax": 1, "Damage": "-", "Action": "Dispon\u00edvel", "Price": 25}, "Q1_011_B": {"Name": "Bermuda de gr\u00e1vida", "Quantity": 1, "Height": 45, "Width": 45, "Depth": 5, "PictureMin": 2, "PictureMax": 2, "Damage": "-", "Action": "Dispon\u00edvel", "Price": 25}, "Q1_012_A": {"Name": "Vestido de festas", "Quantity": 1, "Height": 150, "Width": 30, "Depth": 5, "PictureMin": 1, "PictureMax": 1, "Damage": "-", "Action": "Dispon\u00edvel", "Price": 150}, "Q1_012_B": {"Name": "Vestido de festas", "Quantity": 1, "Height": 140, "Width": 30, "Depth": 5, "PictureMin": 2, "PictureMax": 2, "Damage": "-", "Action": "Dispon\u00edvel", "Price": 150}, "Q1_012_C": {"Name": "Vestido de festas", "Quantity": 1, "Height": 90, "Width": 35, "Depth": 5, "PictureMin": 3, "PictureMax": 3, "Damage": "-", "Action": "Dispon\u00edvel", "Price": 150}, "Q1_012_D": {"Name": "Vestido de festas", "Quantity": 1, "Height": 150, "Width": 35, "Depth": 5, "PictureMin": 4, "PictureMax": 4, "Damage": "-", "Action": "Dispon\u00edvel", "Price": 150}, "Q1_012_E": {"Name": "Vestido de festas", "Quantity": 1, "Height": 150, "Width": 35, "Depth": 5, "PictureMin": 5, "PictureMax": 5, "Damage": "-", "Action": "Dispon\u00edvel", "Price": 150}, "Q1_013": {"Name": "Bota", "Quantity": "4", "Height": 35, "Width": 25, "Depth": 10, "PictureMin": 1, "PictureMax": 1, "Damage": "-", "Action": "Dispon\u00edvel", "Price": 25}, "Q1_014": {"Name": "Trocador de beb\u00ea", "Quantity": 1, "Height": 1, "Width": 70, "Depth": 35, "PictureMin": 1, "PictureMax": 1, "Damage": "-", "Action": "Dispon\u00edvel", "Price": 10}, "Q1_018": {"Name": "Bolsa", "Quantity": "3", "Height": 25, "Width": 40, "Depth": 20, "PictureMin": 1, "PictureMax": 1, "Damage": "-", "Action": "Dispon\u00edvel", "Price": 50}, "Q1_022_A": {"Name": "Edredon", "Quantity": 1, "Height": 240, "Width": 240, "Depth": 5, "PictureMin": 1, "PictureMax": 2, "Damage": "-", "Action": "Dispon\u00edvel", "Price": 50}, "Q1_022_B": {"Name": "Edredon", "Quantity": 1, "Height": 270, "Width": 270, "Depth": 5, "PictureMin": 3, "PictureMax": 3, "Damage": "Costura desfiando", "Action": "Dispon\u00edvel", "Price": 25}, "Q1_025": {"Name": "Babyliss", "Quantity": 1, "Height": 35, "Width": 8, "Depth": 5, "PictureMin": 1, "PictureMax": 1, "Damage": "-", "Action": "Dispon\u00edvel", "Price": 25}, "Q1_030": {"Name": "Co\u00e7ador de costas", "Quantity": 1, "Height": 24, "Width": 3, "Depth": 3, "PictureMin": 1, "PictureMax": 1, "Damage": "-", "Action": "Dispon\u00edvel", "Price": 10}}}, "b1": {"RoomName": "Banheiro 1", "Item": {"B1_031": {"Name": "Balan\u00e7a de pesar", "Quantity": 1, "Height": 3, "Width": 30, "Depth": 30, "PictureMin": 1, "PictureMax": 2, "Damage": "Sem pilha", "Action": "Dispon\u00edvel", "Price": 25}, "B1_032": {"Name": "Saboneteira", "Quantity": 1, "Height": 20, "Width": 7, "Depth": 7, "PictureMin": 1, "PictureMax": 1, "Damage": "Desgate no topo de onde se pressiona", "Action": "Dispon\u00edvel", "Price": 0}, "B1_033": {"Name": "Recipiente para escovas de dente", "Quantity": 1, "Height": 10, "Width": 7, "Depth": 7, "PictureMin": 1, "PictureMax": 1, "Damage": "-", "Action": "Dispon\u00edvel", "Price": 25}}}, "q2": {"RoomName": "Quarto 2", "Item": {"Q2_035_A": {"Name": "Cama e colch\u00e3o", "Quantity": 1, "Height": "45", "Width": 153, "Depth": 83, "PictureMin": 1, "PictureMax": 2, "Damage": "-", "Action": "Dispon\u00edvel", "Price": 300}, "Q2_035_B": {"Name": "Cama e colch\u00e3o", "Quantity": 1, "Height": 46, "Width": 171, "Depth": 94, "PictureMin": 3, "PictureMax": 3, "Damage": "Um estrado quebrado", "Action": "Dispon\u00edvel", "Price": 200}, "Q2_036": {"Name": "Criado-mudo", "Quantity": 1, "Height": 66, "Width": 45, "Depth": 36, "PictureMin": 1, "PictureMax": 1, "Damage": "-", "Action": "Dispon\u00edvel", "Price": 100}, "Q2_037": {"Name": "Tapete", "Quantity": 1, "Height": 72, "Width": 118, "Depth": 1, "PictureMin": 1, "PictureMax": 1, "Damage": "-", "Action": "Dispon\u00edvel", "Price": 25}, "Q2_038": {"Name": "Banco amarelo", "Quantity": 1, "Height": 25, "Width": 35, "Depth": 20, "PictureMin": 1, "PictureMax": 1, "Damage": "-", "Action": "Dispon\u00edvel", "Price": 25}, "Q2_041": {"Name": "Cabide", "Quantity": "18", "Height": 20, "Width": 33, "Depth": 1, "PictureMin": 1, "PictureMax": 1, "Damage": "-", "Action": "Dispon\u00edvel", "Price": 10}, "Q2_042": {"Name": "Almofada", "Quantity": "3", "Height": 25, "Width": 25, "Depth": 12, "PictureMin": 1, "PictureMax": 2, "Damage": "-", "Action": "Dispon\u00edvel", "Price": 25}, "Q2_046": {"Name": "Porta-livros", "Quantity": "2", "Height": 11, "Width": 40, "Depth": 12, "PictureMin": 1, "PictureMax": 2, "Damage": "-", "Action": "Dispon\u00edvel", "Price": 25}, "Q2_055": {"Name": "Kit de capacete Rafa", "Quantity": 1, "Height": 16, "Width": 20, "Depth": 23, "PictureMin": 1, "PictureMax": 1, "Damage": "-", "Action": "Dispon\u00edvel", "Price": 25}, "Q2_056": {"Name": "Edredon", "Quantity": 1, "Height": 240, "Width": 180, "Depth": 5, "PictureMin": 1, "PictureMax": 1, "Damage": "-", "Action": "Dispon\u00edvel", "Price": 50}, "Q2_058": {"Name": "Colcha", "Quantity": 1, "Height": 210, "Width": 130, "Depth": 1, "PictureMin": 1, "PictureMax": 1, "Damage": "-", "Action": "Dispon\u00edvel", "Price": 25}, "Q2_062": {"Name": "Kit de capacete Biel", "Quantity": 1, "Height": 16, "Width": 20, "Depth": 23, "PictureMin": 1, "PictureMax": 1, "Damage": "-", "Action": "Dispon\u00edvel", "Price": 25}}}, "b2": {"RoomName": "Banheiro 2", "Item": {"B2_065": {"Name": "Banquinho verde", "Quantity": 1, "Height": 26, "Width": 33, "Depth": 27, "PictureMin": 1, "PictureMax": 2, "Damage": "Dobradi\u00e7a quebrada", "Action": "Dispon\u00edvel", "Price": 0}, "B2_068": {"Name": "Tapete anti-derrapante", "Quantity": 1, "Height": 1, "Width": 70, "Depth": 40, "PictureMin": 1, "PictureMax": 1, "Damage": "-", "Action": "Dispon\u00edvel", "Price": 10}}}, "q3": {"RoomName": "Quarto 3", "Item": {"Q3_071": {"Name": "Brinquedo", "Quantity": "n", "Height": 35, "Width": 135, "Depth": 60, "PictureMin": 1, "PictureMax": 3, "Damage": "-", "Action": "Dispon\u00edvel", "Price": 0}, "Q3_074": {"Name": "Cesto de brinquedos", "Quantity": "10", "Height": 25, "Width": 35, "Depth": 30, "PictureMin": 1, "PictureMax": 1, "Damage": "-", "Action": "Dispon\u00edvel", "Price": 25}, "Q3_075": {"Name": "Tapete", "Quantity": 1, "Height": 95, "Width": 50, "Depth": 1, "PictureMin": 1, "PictureMax": 1, "Damage": "-", "Action": "Dispon\u00edvel", "Price": 10}, "Q3_076": {"Name": "Mesinha para crian\u00e7as", "Quantity": 1, "Height": 57, "Width": 60, "Depth": 60, "PictureMin": 1, "PictureMax": 1, "Damage": "Pequenos riscos", "Action": "Dispon\u00edvel", "Price": 50}, "Q3_077_A": {"Name": "Cadeira para crian\u00e7as", "Quantity": 1, "Height": 58, "Width": 34, "Depth": "36", "PictureMin": 1, "PictureMax": 2, "Damage": "-", "Action": "Dispon\u00edvel", "Price": 25}, "Q3_077_B": {"Name": "Cadeira para crian\u00e7as", "Quantity": 1, "Height": 58, "Width": 28, "Depth": 27, "PictureMin": 3, "PictureMax": 4, "Damage": "-", "Action": "Dispon\u00edvel", "Price": 25}, "Q3_081": {"Name": "Abajur", "Quantity": 1, "Height": 32, "Width": 13, "Depth": 13, "PictureMin": 1, "PictureMax": 2, "Damage": "-", "Action": "Dispon\u00edvel", "Price": 25}, "Q3_082": {"Name": "Lampi\u00e3o", "Quantity": 1, "Height": 12, "Width": 8, "Depth": 6, "PictureMin": 1, "PictureMax": 1, "Damage": "-", "Action": "Dispon\u00edvel", "Price": 0}, "Q3_083_A": {"Name": "Trip\u00e9", "Quantity": 1, "Height": 45, "Width": 20, "Depth": 20, "PictureMin": 1, "PictureMax": 1, "Damage": "-", "Action": "Dispon\u00edvel", "Price": 0}, "Q3_084_A": {"Name": "Colete de piscina", "Quantity": 1, "Height": 15, "Width": 45, "Depth": 10, "PictureMin": 1, "PictureMax": 1, "Damage": "-", "Action": "Dispon\u00edvel", "Price": 0}, "Q3_084_B": {"Name": "Colete de piscina", "Quantity": 1, "Height": 15, "Width": 45, "Depth": 10, "PictureMin": 2, "PictureMax": 2, "Damage": "-", "Action": "Dispon\u00edvel", "Price": 0}, "Q3_085_A": {"Name": "B\u00f3ia de piscina", "Quantity": 1, "Height": 25, "Width": 41, "Depth": 55, "PictureMin": 1, "PictureMax": 1, "Damage": "-", "Action": "Dispon\u00edvel", "Price": 0}, "Q3_085_B": {"Name": "B\u00f3ia de piscina", "Quantity": 1, "Height": 30, "Width": 41, "Depth": 5, "PictureMin": 2, "PictureMax": 2, "Damage": "-", "Action": "Dispon\u00edvel", "Price": 0}}}, "st": {"RoomName": "Sala de TV", "Item": {"ST_101": {"Name": "Cesto para colocar cobertor", "Quantity": 1, "Height": 30, "Width": 40, "Depth": 30, "PictureMin": 1, "PictureMax": 2, "Damage": "-", "Action": "Dispon\u00edvel", "Price": 25}, "ST_103": {"Name": "T\u00e1bua de equil\u00edbrio", "Quantity": 1, "Height": 12, "Width": 40, "Depth": 40, "PictureMin": 1, "PictureMax": 2, "Damage": "-", "Action": "Dispon\u00edvel", "Price": 10}, "ST_104": {"Name": "Bola de areia", "Quantity": 1, "Height": 13, "Width": 13, "Depth": 13, "PictureMin": 1, "PictureMax": 1, "Damage": "-", "Action": "Dispon\u00edvel", "Price": 10}, "ST_105": {"Name": "Cacto de porcelana", "Quantity": "2", "Height": 20, "Width": 20, "Depth": 10, "PictureMin": 1, "PictureMax": 2, "Damage": "-", "Action": "Dispon\u00edvel", "Price": 25}, "ST_106": {"Name": "Vaso oval", "Quantity": 1, "Height": 11, "Width": 12, "Depth": 6, "PictureMin": 1, "PictureMax": 2, "Damage": "-", "Action": "Dispon\u00edvel", "Price": 25}, "ST_107": {"Name": "Tronco de madeira", "Quantity": "2", "Height": 20, "Width": 50, "Depth": 20, "PictureMin": 1, "PictureMax": 2, "Damage": "-", "Action": "Dispon\u00edvel", "Price": 10}, "ST_108": {"Name": "Vaso de planta", "Quantity": 1, "Height": 17, "Width": 20, "Depth": 20, "PictureMin": 1, "PictureMax": 1, "Damage": "-", "Action": "Dispon\u00edvel", "Price": 25}, "ST_109": {"Name": "Apple TV com controle", "Quantity": 1, "Height": 3, "Width": 10, "Depth": 10, "PictureMin": 1, "PictureMax": 2, "Damage": "-", "Action": "Vendido", "Price": 50}, "ST_110": {"Name": "Home-theather", "Quantity": 1, "Height": 40, "Width": 65, "Depth": 35, "PictureMin": 1, "PictureMax": 3, "Damage": "Pequenos riscos externos", "Action": "Dispon\u00edvel", "Price": 100}, "ST_111": {"Name": "Impressora e scanner", "Quantity": 1, "Height": 20, "Width": 45, "Depth": 30, "PictureMin": 1, "PictureMax": 2, "Damage": "Pequenos riscos externos. Sem cartuchos", "Action": "Dispon\u00edvel", "Price": 25}, "ST_112": {"Name": "CD e DVD", "Quantity": "n", "Height": "-", "Width": "-", "Depth": "-", "PictureMin": 1, "PictureMax": 1, "Damage": "-", "Action": "Dispon\u00edvel", "Price": 0}}}, "sl": {"RoomName": "Sala de leitura", "Item": {"SL_115": {"Name": "Mancebo", "Quantity": 1, "Height": 160, "Width": 30, "Depth": 30, "PictureMin": 1, "PictureMax": 1, "Damage": "-", "Action": "Dispon\u00edvel", "Price": 50}, "SL_118": {"Name": "Tronco de madeira", "Quantity": 1, "Height": 20, "Width": 35, "Depth": 35, "PictureMin": 1, "PictureMax": 2, "Damage": "-", "Action": "Dispon\u00edvel", "Price": 25}, "SL_119": {"Name": "Vaso pequeno preto", "Quantity": 1, "Height": 13, "Width": 10, "Depth": 7, "PictureMin": 1, "PictureMax": 2, "Damage": "-", "Action": "Dispon\u00edvel", "Price": 25}, "SL_120": {"Name": "Cabe\u00e7a de Buda", "Quantity": 1, "Height": 27, "Width": 18, "Depth": 17, "PictureMin": 1, "PictureMax": 2, "Damage": "-", "Action": "Dispon\u00edvel", "Price": 25}, "SL_122": {"Name": "Banco de enfeite", "Quantity": 1, "Height": 9, "Width": 9, "Depth": 9, "PictureMin": 1, "PictureMax": 1, "Damage": "Mancha de queimado", "Action": "Dispon\u00edvel", "Price": 10}}}, "se": {"RoomName": "Sala de estar", "Item": {"SE_126": {"Name": "Quadro de rolhas de vinho", "Quantity": 1, "Height": 50, "Width": 25, "Depth": 5, "PictureMin": 1, "PictureMax": 1, "Damage": "-", "Action": "Dispon\u00edvel", "Price": 25}, "SE_128": {"Name": "Tronco de madeira", "Quantity": 1, "Height": 45, "Width": 45, "Depth": 40, "PictureMin": 1, "PictureMax": 3, "Damage": "-", "Action": "Dispon\u00edvel", "Price": 50}, "SE_129_A": {"Name": "Vaso", "Quantity": 1, "Height": "-", "Width": "-", "Depth": "-", "PictureMin": 1, "PictureMax": 1, "Damage": "-", "Action": "Dispon\u00edvel", "Price": 10}, "SE_129_B": {"Name": "Vaso", "Quantity": 1, "Height": "-", "Width": "-", "Depth": "-", "PictureMin": 2, "PictureMax": 2, "Damage": "-", "Action": "Dispon\u00edvel", "Price": 10}, "SE_129_C": {"Name": "Vaso", "Quantity": 1, "Height": "-", "Width": "-", "Depth": "-", "PictureMin": 3, "PictureMax": 3, "Damage": "-", "Action": "Dispon\u00edvel", "Price": 10}, "SE_130": {"Name": "Casti\u00e7al", "Quantity": 1, "Height": 18, "Width": 10, "Depth": 10, "PictureMin": 1, "PictureMax": 1, "Damage": "-", "Action": "Dispon\u00edvel", "Price": 10}, "SE_131": {"Name": "Abridor de vinho", "Quantity": 1, "Height": 10, "Width": 25, "Depth": 15, "PictureMin": 1, "PictureMax": 2, "Damage": "Pequenos riscos externos", "Action": "Dispon\u00edvel", "Price": 25}, "SE_132": {"Name": "Jogo de Poker", "Quantity": 1, "Height": 12, "Width": 24, "Depth": 12, "PictureMin": 1, "PictureMax": 1, "Damage": "Algumas cartas est\u00e3o amassadas/dobradas", "Action": "Dispon\u00edvel", "Price": 25}, "SE_133": {"Name": "Massageador", "Quantity": 1, "Height": 20, "Width": 30, "Depth": 10, "PictureMin": 1, "PictureMax": 3, "Damage": "-", "Action": "Dispon\u00edvel", "Price": 100}}}, "sj": {"RoomName": "Sala de jantar", "Item": {"SJ_134": {"Name": "Cadeir\u00e3o", "Quantity": 1, "Height": 75, "Width": 50, "Depth": 50, "PictureMin": 1, "PictureMax": 3, "Damage": "-", "Action": "Dispon\u00edvel", "Price": 50}, "SJ_135": {"Name": "Gamela de madeira", "Quantity": 1, "Height": 10, "Width": 40, "Depth": 30, "PictureMin": 1, "PictureMax": 2, "Damage": "-", "Action": "Dispon\u00edvel", "Price": 25}, "SJ_136": {"Name": "Vaso grande de planta", "Quantity": 1, "Height": 160, "Width": 40, "Depth": 40, "PictureMin": 1, "PictureMax": 2, "Damage": "-", "Action": "Dispon\u00edvel", "Price": 50}, "SJ_137": {"Name": "Rod\u00edzio", "Quantity": 1, "Height": 7, "Width": 30, "Depth": 30, "PictureMin": 1, "PictureMax": 2, "Damage": "-", "Action": "Dispon\u00edvel", "Price": 25}, "SJ_138": {"Name": "Carrinho de ch\u00e1", "Quantity": 1, "Height": 85, "Width": 75, "Depth": 35, "PictureMin": 1, "PictureMax": 2, "Damage": "-", "Action": "Dispon\u00edvel", "Price": 50}, "SJ_139": {"Name": "Cafeteira Nespresso", "Quantity": 1, "Height": 22, "Width": 33, "Depth": 10, "PictureMin": 1, "PictureMax": 2, "Damage": "-", "Action": "Reservado", "Price": 230}, "SJ_140": {"Name": "Leiteira Nespresso", "Quantity": 1, "Height": 20, "Width": 10, "Depth": 10, "PictureMin": 1, "PictureMax": 2, "Damage": "-", "Action": "Dispon\u00edvel", "Price": 100}, "SJ_141": {"Name": "Porta-c\u00e1psulas", "Quantity": 1, "Height": 13, "Width": 13, "Depth": 13, "PictureMin": 1, "PictureMax": 2, "Damage": "-", "Action": "Reservado", "Price": 0}, "SJ_142": {"Name": "Porta-guardanapos", "Quantity": 1, "Height": 10, "Width": 12, "Depth": 6, "PictureMin": 1, "PictureMax": 1, "Damage": "-", "Action": "Dispon\u00edvel", "Price": 0}, "SJ_143": {"Name": "Estatueta da Ana e Elza", "Quantity": 1, "Height": 60, "Width": 65, "Depth": 20, "PictureMin": 1, "PictureMax": 1, "Damage": "-", "Action": "Vendido", "Price": 0}, "SJ_144": {"Name": "Bandeija de borboleta", "Quantity": 1, "Height": 20, "Width": 60, "Depth": 25, "PictureMin": 1, "PictureMax": 2, "Damage": "-", "Action": "Dispon\u00edvel", "Price": 25}, "SJ_145": {"Name": "Ta\u00e7a de vinho", "Quantity": "4", "Height": 23, "Width": 10, "Depth": 10, "PictureMin": 1, "PictureMax": 1, "Damage": "-", "Action": "Dispon\u00edvel", "Price": 25}, "SJ_146": {"Name": "Vaso de flor seca", "Quantity": 1, "Height": 20, "Width": 15, "Depth": 15, "PictureMin": 1, "PictureMax": 2, "Damage": "-", "Action": "Vendido", "Price": 25}, "SJ_147": {"Name": "Vaso de planta/areia", "Quantity": 1, "Height": 10, "Width": 13, "Depth": 13, "PictureMin": 1, "PictureMax": 1, "Damage": "-", "Action": "Dispon\u00edvel", "Price": 25}, "SJ_148": {"Name": "Tronco de madeira", "Quantity": "2", "Height": 3, "Width": 40, "Depth": 25, "PictureMin": 1, "PictureMax": 1, "Damage": "-", "Action": "Dispon\u00edvel", "Price": 10}, "SJ_149": {"Name": "Porta-vela", "Quantity": 1, "Height": 20, "Width": 12, "Depth": 12, "PictureMin": 1, "PictureMax": 1, "Damage": "-", "Action": "Dispon\u00edvel", "Price": 0}, "SJ_150_A": {"Name": "Vaso", "Quantity": 1, "Height": 13, "Width": 11, "Depth": 11, "PictureMin": 1, "PictureMax": 1, "Damage": "-", "Action": "Dispon\u00edvel", "Price": 10}, "SJ_150_B": {"Name": "Vaso", "Quantity": 1, "Height": 20, "Width": 20, "Depth": 13, "PictureMin": 2, "PictureMax": 2, "Damage": "-", "Action": "Vendido", "Price": 0}, "SJ_151": {"Name": "Jogo americano retangular", "Quantity": "6", "Height": 1, "Width": 45, "Depth": 30, "PictureMin": 1, "PictureMax": 1, "Damage": "-", "Action": "Dispon\u00edvel", "Price": 25}, "SJ_152": {"Name": "Suplat", "Quantity": "6", "Height": 2, "Width": 33, "Depth": 33, "PictureMin": 1, "PictureMax": 2, "Damage": "-", "Action": "Dispon\u00edvel", "Price": 50}, "SJ_153": {"Name": "Jogo americano redondo", "Quantity": "6", "Height": 1, "Width": 38, "Depth": 38, "PictureMin": 1, "PictureMax": 2, "Damage": "-", "Action": "Reservado", "Price": 0}, "SJ_154": {"Name": "Abridor de vinho", "Quantity": 1, "Height": 18, "Width": 8, "Depth": 3, "PictureMin": 1, "PictureMax": 1, "Damage": "-", "Action": "Dispon\u00edvel", "Price": 10}, "SJ_155": {"Name": "Casti\u00e7al", "Quantity": "7", "Height": 14, "Width": 10, "Depth": 10, "PictureMin": 1, "PictureMax": 2, "Damage": "-", "Action": "Dispon\u00edvel", "Price": 25}, "SJ_156": {"Name": "Porta-guardanapos individual", "Quantity": "6", "Height": 2, "Width": 5, "Depth": 5, "PictureMin": 1, "PictureMax": 2, "Damage": "-", "Action": "Dispon\u00edvel", "Price": 25}, "SJ_157": {"Name": "Porta-talheres", "Quantity": "2", "Height": 5, "Width": 33, "Depth": 30, "PictureMin": 1, "PictureMax": 1, "Damage": "-", "Action": "Dispon\u00edvel", "Price": 10}, "SJ_158": {"Name": "Porta-copos", "Quantity": "7", "Height": 1, "Width": 10, "Depth": 10, "PictureMin": 1, "PictureMax": 1, "Damage": "-", "Action": "Dispon\u00edvel", "Price": 25}, "SJ_159_A": {"Name": "Talher", "Quantity": "n", "Height": "-", "Width": "-", "Depth": "-", "PictureMin": 1, "PictureMax": 1, "Damage": "-", "Action": "Dispon\u00edvel", "Price": 75}, "SJ_159_B": {"Name": "Talher", "Quantity": "n", "Height": "-", "Width": "-", "Depth": "-", "PictureMin": 2, "PictureMax": 2, "Damage": "-", "Action": "Dispon\u00edvel", "Price": 50}, "SJ_159_D": {"Name": "Talher", "Quantity": "n", "Height": "-", "Width": "-", "Depth": "-", "PictureMin": 4, "PictureMax": 4, "Damage": "-", "Action": "Dispon\u00edvel", "Price": 25}, "SJ_160_A": {"Name": "Prato", "Quantity": "n", "Height": 3, "Width": 26, "Depth": 26, "PictureMin": 1, "PictureMax": 1, "Damage": "-", "Action": "Dispon\u00edvel", "Price": 100}, "SJ_160_B": {"Name": "Prato", "Quantity": 10, "Height": 3, "Width": 20, "Depth": 20, "PictureMin": 2, "PictureMax": 2, "Damage": "-", "Action": "Dispon\u00edvel", "Price": 100}, "SJ_160_C": {"Name": "Prato", "Quantity": 6, "Height": 3, "Width": 20, "Depth": 20, "PictureMin": 3, "PictureMax": 3, "Damage": "-", "Action": "Dispon\u00edvel", "Price": 50}, "SJ_161": {"Name": "Geleira", "Quantity": 1, "Height": 18, "Width": 18, "Depth": 15, "PictureMin": 1, "PictureMax": 1, "Damage": "-", "Action": "Dispon\u00edvel", "Price": 10}, "SJ_162_A": {"Name": "Decanter", "Quantity": 1, "Height": 25, "Width": 22, "Depth": 22, "PictureMin": 1, "PictureMax": 1, "Damage": "-", "Action": "Dispon\u00edvel", "Price": 10}, "SJ_162_B": {"Name": "Decanter", "Quantity": 1, "Height": 25, "Width": 11, "Depth": 11, "PictureMin": 2, "PictureMax": 2, "Damage": "-", "Action": "Dispon\u00edvel", "Price": 10}, "SJ_163": {"Name": "Term\u00f4metro de vinho", "Quantity": 1, "Height": 17, "Width": 9, "Depth": 5, "PictureMin": 1, "PictureMax": 1, "Damage": "-", "Action": "Dispon\u00edvel", "Price": 0}, "SJ_164_A": {"Name": "Copo", "Quantity": 10, "Height": 14, "Width": 9, "Depth": 9, "PictureMin": 1, "PictureMax": 1, "Damage": "-", "Action": "Dispon\u00edvel", "Price": 100}, "SJ_164_B": {"Name": "Copo", "Quantity": 4, "Height": 7, "Width": 8, "Depth": 8, "PictureMin": 2, "PictureMax": 2, "Damage": "-", "Action": "Dispon\u00edvel", "Price": 50}, "SJ_164_C": {"Name": "Copo", "Quantity": 6, "Height": 17, "Width": 9, "Depth": 9, "PictureMin": 3, "PictureMax": 3, "Damage": "-", "Action": "Dispon\u00edvel", "Price": 50}, "SJ_165": {"Name": "Toalha de mesa", "Quantity": "3", "Height": 1, "Width": 115, "Depth": 190, "PictureMin": 1, "PictureMax": 1, "Damage": "-", "Action": "Dispon\u00edvel", "Price": 50}}}, "lb": {"RoomName": "Lavabo", "Item": {"LB_166": {"Name": "Cesto de palha", "Quantity": 1, "Height": 10, "Width": 30, "Depth": 30, "PictureMin": 1, "PictureMax": 1, "Damage": "-", "Action": "Dispon\u00edvel", "Price": 25}, "LB_167": {"Name": "Caixa com flores artificiais", "Quantity": 1, "Height": 10, "Width": 25, "Depth": 12, "PictureMin": 1, "PictureMax": 2, "Damage": "-", "Action": "Dispon\u00edvel", "Price": 25}}}, "ag": {"RoomName": "\u00c1rea gourmet", "Item": {"AG_168": {"Name": "Rede de gatos", "Quantity": 1, "Height": 1, "Width": 50, "Depth": 50, "PictureMin": 1, "PictureMax": 2, "Damage": "-", "Action": "Dispon\u00edvel", "Price": 25}, "AG_170": {"Name": "Quadro de plantas", "Quantity": 1, "Height": 55, "Width": 95, "Depth": 25, "PictureMin": 1, "PictureMax": 2, "Damage": "-", "Action": "Dispon\u00edvel", "Price": 25}, "AG_171": {"Name": "Bicicleta de madeira", "Quantity": 1, "Height": 50, "Width": 100, "Depth": 40, "PictureMin": 1, "PictureMax": 1, "Damage": "-", "Action": "Vendido", "Price": 250}, "AG_172_A": {"Name": "Bola", "Quantity": 1, "Height": 20, "Width": "-", "Depth": "-", "PictureMin": 1, "PictureMax": 1, "Damage": "Murcha", "Action": "Dispon\u00edvel", "Price": 0}, "AG_172_B": {"Name": "Bola", "Quantity": 1, "Height": 14, "Width": "-", "Depth": "-", "PictureMin": 2, "PictureMax": 2, "Damage": "Murcha", "Action": "Dispon\u00edvel", "Price": 25}, "AG_173": {"Name": "Bebedouro de gatos", "Quantity": 1, "Height": 18, "Width": 22, "Depth": 27, "PictureMin": 1, "PictureMax": 2, "Damage": "-", "Action": "Dispon\u00edvel", "Price": 0}, "AG_176": {"Name": "Cabe\u00e7a de Buda", "Quantity": 1, "Height": 22, "Width": 12, "Depth": 12, "PictureMin": 1, "PictureMax": 2, "Damage": "-", "Action": "Dispon\u00edvel", "Price": 50}, "AG_177": {"Name": "M\u00f3bile para jardim", "Quantity": 1, "Height": 60, "Width": 15, "Depth": 15, "PictureMin": 1, "PictureMax": 1, "Damage": "-", "Action": "Dispon\u00edvel", "Price": 0}, "AG_178": {"Name": "Bebedouro de \u00e1gua/suco", "Quantity": 1, "Height": 55, "Width": 25, "Depth": 25, "PictureMin": 1, "PictureMax": 3, "Damage": "-", "Action": "Dispon\u00edvel", "Price": 200}, "AG_179": {"Name": "Balde com folhas secas", "Quantity": 1, "Height": 40, "Width": 25, "Depth": 15, "PictureMin": 1, "PictureMax": 1, "Damage": "-", "Action": "Dispon\u00edvel", "Price": 10}, "AG_180": {"Name": "Vaso-l\u00e2mpada", "Quantity": "2", "Height": 18, "Width": 10, "Depth": 10, "PictureMin": 1, "PictureMax": 1, "Damage": "-", "Action": "Dispon\u00edvel", "Price": 10}, "AG_185": {"Name": "Utens\u00edlios para churrasco", "Quantity": 1, "Height": 45, "Width": 40, "Depth": 3, "PictureMin": 1, "PictureMax": 1, "Damage": "-", "Action": "Dispon\u00edvel", "Price": 50}, "AG_186": {"Name": "Talher", "Quantity": "n", "Height": 50, "Width": 40, "Depth": 2, "PictureMin": 1, "PictureMax": 1, "Damage": "-", "Action": "Dispon\u00edvel", "Price": 100}, "AG_187": {"Name": "Vaso-cora\u00e7\u00e3o", "Quantity": 1, "Height": 11, "Width": 11, "Depth": 4, "PictureMin": 1, "PictureMax": 2, "Damage": "-", "Action": "Vendido", "Price": 25}}}, "cz": {"RoomName": "Cozinha", "Item": {"CZ_188": {"Name": "Fruteira em formato de morango", "Quantity": 1, "Height": 28, "Width": 27, "Depth": 27, "PictureMin": 1, "PictureMax": 1, "Damage": "-", "Action": "Dispon\u00edvel", "Price": 25}, "CZ_189_A": {"Name": "Ponche", "Quantity": 6, "Height": 11, "Width": 25, "Depth": 25, "PictureMin": 1, "PictureMax": 2, "Damage": "-", "Action": "Dispon\u00edvel", "Price": 25}, "CZ_189_B": {"Name": "Ponche", "Quantity": 5, "Height": 16, "Width": 19, "Depth": 19, "PictureMin": 3, "PictureMax": 4, "Damage": "-", "Action": "Dispon\u00edvel", "Price": 25}, "CZ_190_A": {"Name": "Pote de sobremesa", "Quantity": 6, "Height": 12, "Width": 12, "Depth": 12, "PictureMin": 1, "PictureMax": 2, "Damage": "-", "Action": "Dispon\u00edvel", "Price": 25}, "CZ_190_B": {"Name": "Pote de sobremesa", "Quantity": 2, "Height": 20, "Width": 9, "Depth": 9, "PictureMin": 3, "PictureMax": 3, "Damage": "-", "Action": "Dispon\u00edvel", "Price": 25}, "CZ_191": {"Name": "Ta\u00e7a de champanhe", "Quantity": 5, "Height": 24, "Width": 6, "Depth": 6, "PictureMin": 1, "PictureMax": 1, "Damage": "-", "Action": "Dispon\u00edvel", "Price": 50}, "CZ_192_A": {"Name": "Ta\u00e7a de vinho", "Quantity": 3, "Height": 24, "Width": 9, "Depth": 9, "PictureMin": 1, "PictureMax": 1, "Damage": "-", "Action": "Dispon\u00edvel", "Price": 50}, "CZ_192_B": {"Name": "Ta\u00e7a de vinho", "Quantity": 5, "Height": 23, "Width": 8, "Depth": 8, "PictureMin": 2, "PictureMax": 2, "Damage": "-", "Action": "Dispon\u00edvel", "Price": 50}, "CZ_193_A": {"Name": "Copo", "Quantity": 3, "Height": 18, "Width": 7, "Depth": 7, "PictureMin": 1, "PictureMax": 1, "Damage": "-", "Action": "Dispon\u00edvel", "Price": 25}, "CZ_193_B": {"Name": "Copo", "Quantity": 3, "Height": 14, "Width": 7, "Depth": 7, "PictureMin": 2, "PictureMax": 2, "Damage": "-", "Action": "Dispon\u00edvel", "Price": 50}, "CZ_193_C": {"Name": "Copo", "Quantity": 3, "Height": 13, "Width": 6, "Depth": 6, "PictureMin": 3, "PictureMax": 3, "Damage": "-", "Action": "Dispon\u00edvel", "Price": 25}, "CZ_193_D": {"Name": "Copo", "Quantity": 5, "Height": 9, "Width": 7, "Depth": 7, "PictureMin": 4, "PictureMax": 4, "Damage": "-", "Action": "Dispon\u00edvel", "Price": 25}, "CZ_193_E": {"Name": "Copo", "Quantity": 2, "Height": 14, "Width": 9, "Depth": 9, "PictureMin": 5, "PictureMax": 5, "Damage": "-", "Action": "Dispon\u00edvel", "Price": 25}, "CZ_193_F": {"Name": "Copo", "Quantity": 3, "Height": 19, "Width": 8, "Depth": 8, "PictureMin": 6, "PictureMax": 6, "Damage": "-", "Action": "Dispon\u00edvel", "Price": 25}, "CZ_193_G": {"Name": "Copo", "Quantity": 2, "Height": 20, "Width": 6, "Depth": 6, "PictureMin": 7, "PictureMax": 7, "Damage": "-", "Action": "Dispon\u00edvel", "Price": 10}, "CZ_194_A": {"Name": "Prato", "Quantity": "n", "Height": 3, "Width": 26, "Depth": 26, "PictureMin": 1, "PictureMax": 2, "Damage": "-", "Action": "Dispon\u00edvel", "Price": 0}, "CZ_194_B": {"Name": "Prato", "Quantity": "n", "Height": 3, "Width": 28, "Depth": 28, "PictureMin": 3, "PictureMax": 4, "Damage": "-", "Action": "Dispon\u00edvel", "Price": 50}, "CZ_195_A": {"Name": "Prato de bolo", "Quantity": 1, "Height": 2, "Width": 28, "Depth": 28, "PictureMin": 1, "PictureMax": 1, "Damage": "-", "Action": "Dispon\u00edvel", "Price": 10}, "CZ_195_B": {"Name": "Prato de bolo", "Quantity": 1, "Height": 3, "Width": 31, "Depth": 31, "PictureMin": 2, "PictureMax": 2, "Damage": "-", "Action": "Dispon\u00edvel", "Price": 10}, "CZ_195_C": {"Name": "Prato de bolo", "Quantity": 1, "Height": 2, "Width": 30, "Depth": 30, "PictureMin": 3, "PictureMax": 3, "Damage": "-", "Action": "Dispon\u00edvel", "Price": 10}, "CZ_196_A": {"Name": "Prato com pratinhos de bolo", "Quantity": 1, "Height": 4, "Width": 30, "Depth": 30, "PictureMin": 1, "PictureMax": 1, "Damage": "-", "Action": "Dispon\u00edvel", "Price": 25}, "CZ_196_B": {"Name": "Prato com pratinhos de bolo", "Quantity": 1, "Height": 2, "Width": 30, "Depth": 30, "PictureMin": 2, "PictureMax": 2, "Damage": "-", "Action": "Dispon\u00edvel", "Price": 25}, "CZ_197_A": {"Name": "Bowl", "Quantity": 1, "Height": 9, "Width": 20, "Depth": 20, "PictureMin": 1, "PictureMax": 2, "Damage": "-", "Action": "Dispon\u00edvel", "Price": 25}, "CZ_197_B": {"Name": "Bowl", "Quantity": 2, "Height": 8, "Width": 14, "Depth": 14, "PictureMin": 3, "PictureMax": 4, "Damage": "-", "Action": "Dispon\u00edvel", "Price": 25}, "CZ_197_C": {"Name": "Bowl", "Quantity": 1, "Height": 8, "Width": 12, "Depth": 12, "PictureMin": 5, "PictureMax": 5, "Damage": "-", "Action": "Dispon\u00edvel", "Price": 10}, "CZ_197_D": {"Name": "Bowl", "Quantity": 1, "Height": 7, "Width": 15, "Depth": 15, "PictureMin": 6, "PictureMax": 7, "Damage": "-", "Action": "Dispon\u00edvel", "Price": 10}, "CZ_198_A": {"Name": "Porta-petisco", "Quantity": 1, "Height": 8, "Width": 14, "Depth": 14, "PictureMin": 1, "PictureMax": 2, "Damage": "-", "Action": "Dispon\u00edvel", "Price": 25}, "CZ_198_B": {"Name": "Porta-petisco", "Quantity": 1, "Height": 5, "Width": 17, "Depth": 17, "PictureMin": 3, "PictureMax": 4, "Damage": "-", "Action": "Dispon\u00edvel", "Price": 10}, "CZ_199_A": {"Name": "Travessa", "Quantity": 1, "Height": 3, "Width": 38, "Depth": 8, "PictureMin": 1, "PictureMax": 1, "Damage": "-", "Action": "Dispon\u00edvel", "Price": 25}, "CZ_199_B": {"Name": "Travessa", "Quantity": 1, "Height": 2, "Width": 29, "Depth": 12, "PictureMin": 2, "PictureMax": 2, "Damage": "-", "Action": "Dispon\u00edvel", "Price": 25}, "CZ_199_C": {"Name": "Travessa", "Quantity": 1, "Height": 3, "Width": 22, "Depth": 14, "PictureMin": 3, "PictureMax": 3, "Damage": "-", "Action": "Dispon\u00edvel", "Price": 10}, "CZ_200": {"Name": "Meleira", "Quantity": 1, "Height": 12, "Width": 9, "Depth": 9, "PictureMin": 1, "PictureMax": 1, "Damage": "-", "Action": "Dispon\u00edvel", "Price": 25}, "CZ_201_A": {"Name": "Talher", "Quantity": "n", "Height": 18, "Width": 4, "Depth": 2, "PictureMin": 1, "PictureMax": 1, "Damage": "-", "Action": "Dispon\u00edvel", "Price": 25}, "CZ_201_B": {"Name": "Talher", "Quantity": "n", "Height": 15, "Width": 2, "Depth": 1, "PictureMin": 2, "PictureMax": 2, "Damage": "-", "Action": "Dispon\u00edvel", "Price": 25}, "CZ_201_C": {"Name": "Talher", "Quantity": "n", "Height": 27, "Width": 4, "Depth": 2, "PictureMin": 3, "PictureMax": 3, "Damage": "-", "Action": "Dispon\u00edvel", "Price": 25}, "CZ_201_D": {"Name": "Talher", "Quantity": "n", "Height": 16, "Width": 3, "Depth": 2, "PictureMin": 4, "PictureMax": 4, "Damage": "-", "Action": "Dispon\u00edvel", "Price": 0}, "CZ_201_E": {"Name": "Talher", "Quantity": "n", "Height": 15, "Width": 3, "Depth": 2, "PictureMin": 5, "PictureMax": 5, "Damage": "-", "Action": "Dispon\u00edvel", "Price": 0}, "CZ_202": {"Name": "Porta-talheres", "Quantity": 1, "Height": 8, "Width": 30, "Depth": 41, "PictureMin": 1, "PictureMax": 1, "Damage": "-", "Action": "Dispon\u00edvel", "Price": 10}, "CZ_203": {"Name": "Term\u00f4metro de chocolate", "Quantity": 1, "Height": 20, "Width": 2, "Depth": 2, "PictureMin": 1, "PictureMax": 1, "Damage": "-", "Action": "Dispon\u00edvel", "Price": 25}, "CZ_211_A": {"Name": "Ralador", "Quantity": 1, "Height": 30, "Width": 9, "Depth": 2, "PictureMin": 1, "PictureMax": 1, "Damage": "-", "Action": "Dispon\u00edvel", "Price": 0}, "CZ_211_B": {"Name": "Ralador", "Quantity": 1, "Height": 25, "Width": 11, "Depth": 11, "PictureMin": 2, "PictureMax": 2, "Damage": "-", "Action": "Dispon\u00edvel", "Price": 0}, "CZ_204": {"Name": "Afiador de faca", "Quantity": 1, "Height": 5, "Width": 18, "Depth": 6, "PictureMin": 1, "PictureMax": 1, "Damage": "-", "Action": "Dispon\u00edvel", "Price": 0}, "CZ_206": {"Name": "Faca para queijo", "Quantity": "4", "Height": 13, "Width": 5, "Depth": 3, "PictureMin": 1, "PictureMax": 1, "Damage": "-", "Action": "Dispon\u00edvel", "Price": 25}, "CZ_207": {"Name": "Bolador", "Quantity": 1, "Height": 18, "Width": 3, "Depth": 3, "PictureMin": 1, "PictureMax": 1, "Damage": "-", "Action": "Dispon\u00edvel", "Price": 10}, "CZ_208": {"Name": "Rolo", "Quantity": "2", "Height": 5, "Width": 39, "Depth": 5, "PictureMin": 1, "PictureMax": 1, "Damage": "-", "Action": "Dispon\u00edvel", "Price": 10}, "CZ_209": {"Name": "Espremedor de alho", "Quantity": 1, "Height": 6, "Width": 20, "Depth": 4, "PictureMin": 1, "PictureMax": 1, "Damage": "-", "Action": "Dispon\u00edvel", "Price": 0}, "CZ_216": {"Name": "Pegador de comida", "Quantity": "n", "Height": 21, "Width": 5, "Depth": 5, "PictureMin": 1, "PictureMax": 1, "Damage": "-", "Action": "Dispon\u00edvel", "Price": 10}, "CZ_212": {"Name": "Cortador de bolo", "Quantity": 1, "Height": 27, "Width": 6, "Depth": 3, "PictureMin": 1, "PictureMax": 1, "Damage": "-", "Action": "Dispon\u00edvel", "Price": 10}, "CZ_214": {"Name": "Espremedor de batata", "Quantity": 1, "Height": 9, "Width": 22, "Depth": 9, "PictureMin": 1, "PictureMax": 1, "Damage": "-", "Action": "Dispon\u00edvel", "Price": 25}, "CZ_299": {"Name": "Descascador de batata", "Quantity": 1, "Height": 17, "Width": 3, "Depth": 3, "PictureMin": 1, "PictureMax": 1, "Damage": "-", "Action": "Dispon\u00edvel", "Price": 10}, "CZ_215": {"Name": "Esp\u00e1tula de inox", "Quantity": 1, "Height": 13, "Width": 16, "Depth": 3, "PictureMin": 1, "PictureMax": 1, "Damage": "-", "Action": "Dispon\u00edvel", "Price": 25}, "CZ_213": {"Name": "Peneira", "Quantity": 1, "Height": 23, "Width": 10, "Depth": 5, "PictureMin": 1, "PictureMax": 1, "Damage": "-", "Action": "Dispon\u00edvel", "Price": 10}, "CZ_210_A": {"Name": "Colher de servir", "Quantity": "n", "Height": 34, "Width": 7, "Depth": 5, "PictureMin": 1, "PictureMax": 1, "Damage": "-", "Action": "Dispon\u00edvel", "Price": 25}, "CZ_210_B": {"Name": "Colher de servir", "Quantity": "n", "Height": 35, "Width": 8, "Depth": 3, "PictureMin": 2, "PictureMax": 2, "Damage": "-", "Action": "Dispon\u00edvel", "Price": 25}, "CZ_210_C": {"Name": "Colher de servir", "Quantity": "n", "Height": 28, "Width": 8, "Depth": 3, "PictureMin": 3, "PictureMax": 3, "Damage": "-", "Action": "Dispon\u00edvel", "Price": 25}, "CZ_217": {"Name": "P\u00e3o duro", "Quantity": "2", "Height": 27, "Width": 6, "Depth": 2, "PictureMin": 1, "PictureMax": 1, "Damage": "-", "Action": "Dispon\u00edvel", "Price": 10}, "CZ_218": {"Name": "Pincel de comida", "Quantity": 1, "Height": 30, "Width": 5, "Depth": 2, "PictureMin": 1, "PictureMax": 1, "Damage": "-", "Action": "Dispon\u00edvel", "Price": 25}, "CZ_219_A": {"Name": "Toalha de mesa", "Quantity": "n", "Height": 1, "Width": 180, "Depth": 140, "PictureMin": 1, "PictureMax": 2, "Damage": "-", "Action": "Dispon\u00edvel", "Price": 25}, "CZ_219_B": {"Name": "Toalha de mesa", "Quantity": "n", "Height": 1, "Width": 220, "Depth": 140, "PictureMin": 3, "PictureMax": 5, "Damage": "-", "Action": "Dispon\u00edvel", "Price": 25}, "CZ_219_C": {"Name": "Toalha de mesa", "Quantity": "n", "Height": 1, "Width": 135, "Depth": 135, "PictureMin": 6, "PictureMax": 7, "Damage": "-", "Action": "Dispon\u00edvel", "Price": 25}, "CZ_219_D": {"Name": "Toalha de mesa", "Quantity": "n", "Height": 1, "Width": 45, "Depth": 36, "PictureMin": 8, "PictureMax": 8, "Damage": "-", "Action": "Dispon\u00edvel", "Price": 10}, "CZ_219_E": {"Name": "Toalha de mesa", "Quantity": "n", "Height": 1, "Width": 68, "Depth": 63, "PictureMin": 9, "PictureMax": 9, "Damage": "-", "Action": "Dispon\u00edvel", "Price": 0}, "CZ_220_A": {"Name": "Jogo americano", "Quantity": "n", "Height": 1, "Width": 45, "Depth": 30, "PictureMin": 1, "PictureMax": 1, "Damage": "-", "Action": "Dispon\u00edvel", "Price": 0}, "CZ_220_B": {"Name": "Jogo americano", "Quantity": "n", "Height": 1, "Width": 45, "Depth": 30, "PictureMin": 2, "PictureMax": 2, "Damage": "-", "Action": "Dispon\u00edvel", "Price": 0}, "CZ_220_C": {"Name": "Jogo americano", "Quantity": "n", "Height": 1, "Width": 45, "Depth": 33, "PictureMin": 3, "PictureMax": 4, "Damage": "Desfiando", "Action": "Dispon\u00edvel", "Price": 0}, "CZ_221": {"Name": "Torradeira", "Quantity": 1, "Height": 17, "Width": 28, "Depth": 17, "PictureMin": 1, "PictureMax": 1, "Damage": "-", "Action": "Dispon\u00edvel", "Price": 50}, "CZ_222": {"Name": "Marinex", "Quantity": "4", "Height": 12, "Width": 14, "Depth": 14, "PictureMin": 1, "PictureMax": 2, "Damage": "Tampas de pl\u00e1stico rasgadas", "Action": "Dispon\u00edvel", "Price": 50}, "CZ_223": {"Name": "Grade de biscoito", "Quantity": 1, "Height": 2, "Width": 40, "Depth": 25, "PictureMin": 1, "PictureMax": 1, "Damage": "-", "Action": "Dispon\u00edvel", "Price": 25}, "CZ_224": {"Name": "Travessa inox", "Quantity": "2", "Height": 4, "Width": 25, "Depth": 18, "PictureMin": 1, "PictureMax": 1, "Damage": "-", "Action": "Dispon\u00edvel", "Price": 25}, "CZ_225": {"Name": "Saladeira", "Quantity": 1, "Height": 10, "Width": 20, "Depth": 20, "PictureMin": 1, "PictureMax": 1, "Damage": "-", "Action": "Dispon\u00edvel", "Price": 25}, "CZ_226": {"Name": "Assadeira de bolo", "Quantity": 1, "Height": 8, "Width": 21, "Depth": 21, "PictureMin": 1, "PictureMax": 1, "Damage": "-", "Action": "Dispon\u00edvel", "Price": 10}, "CZ_227_A": {"Name": "Travessa de vidro", "Quantity": 1, "Height": 5, "Width": 39, "Depth": 24, "PictureMin": 1, "PictureMax": 2, "Damage": "-", "Action": "Dispon\u00edvel", "Price": 25}, "CZ_227_B": {"Name": "Travessa de vidro", "Quantity": 1, "Height": 6, "Width": 30, "Depth": 19, "PictureMin": 3, "PictureMax": 3, "Damage": "-", "Action": "Dispon\u00edvel", "Price": 25}, "CZ_227_C": {"Name": "Travessa de vidro", "Quantity": 1, "Height": 6, "Width": 26, "Depth": 26, "PictureMin": 4, "PictureMax": 4, "Damage": "-", "Action": "Dispon\u00edvel", "Price": 10}, "CZ_227_D": {"Name": "Travessa de vidro", "Quantity": 1, "Height": 7, "Width": 17, "Depth": 17, "PictureMin": 5, "PictureMax": 5, "Damage": "-", "Action": "Dispon\u00edvel", "Price": 10}, "CZ_228": {"Name": "Panela de press\u00e3o", "Quantity": 1, "Height": 21, "Width": 44, "Depth": 23, "PictureMin": 1, "PictureMax": 2, "Damage": "-", "Action": "Reservado", "Price": 40}, "CZ_229": {"Name": "Panela de macarr\u00e3o", "Quantity": 1, "Height": 20, "Width": 34, "Depth": 23, "PictureMin": 1, "PictureMax": 2, "Damage": "-", "Action": "Dispon\u00edvel", "Price": 50}, "CZ_230": {"Name": "Panela para yakissoba", "Quantity": 1, "Height": 15, "Width": 40, "Depth": 35, "PictureMin": 1, "PictureMax": 2, "Damage": "Pequenos riscos internos", "Action": "Dispon\u00edvel", "Price": 50}, "CZ_231": {"Name": "Air-fryer", "Quantity": 1, "Height": 35, "Width": 25, "Depth": 30, "PictureMin": 1, "PictureMax": 3, "Damage": "Plug sem acabamento", "Action": "Vendido", "Price": 100}, "CZ_232_A": {"Name": "Descanso de panela", "Quantity": 1, "Height": 1, "Width": 18, "Depth": 18, "PictureMin": 1, "PictureMax": 1, "Damage": "-", "Action": "Dispon\u00edvel", "Price": 0}, "CZ_232_B": {"Name": "Descanso de panela", "Quantity": 1, "Height": 1, "Width": 33, "Depth": 27, "PictureMin": 2, "PictureMax": 2, "Damage": "-", "Action": "Dispon\u00edvel", "Price": 0}, "CZ_233_A": {"Name": "Luva de forno", "Quantity": 1, "Height": 8, "Width": 10, "Depth": 13, "PictureMin": 1, "PictureMax": 1, "Damage": "-", "Action": "Dispon\u00edvel", "Price": 0}, "CZ_233_B": {"Name": "Luva de forno", "Quantity": 1, "Height": 28, "Width": 20, "Depth": 3, "PictureMin": 2, "PictureMax": 2, "Damage": "-", "Action": "Dispon\u00edvel", "Price": 0}, "CZ_234": {"Name": "Chaleira", "Quantity": 1, "Height": 24, "Width": 21, "Depth": 19, "PictureMin": 1, "PictureMax": 1, "Damage": "-", "Action": "Dispon\u00edvel", "Price": 25}, "CZ_235": {"Name": "Chaleira el\u00e9trica", "Quantity": 1, "Height": 25, "Width": 25, "Depth": 15, "PictureMin": 1, "PictureMax": 2, "Damage": "-", "Action": "Dispon\u00edvel", "Price": 25}, "CZ_236": {"Name": "Garrafa t\u00e9rmica", "Quantity": "2", "Height": 26, "Width": 16, "Depth": 14, "PictureMin": 1, "PictureMax": 1, "Damage": "-", "Action": "Dispon\u00edvel", "Price": 25}, "CZ_237": {"Name": "Porta-p\u00e3o", "Quantity": 1, "Height": 12, "Width": 21, "Depth": 13, "PictureMin": 1, "PictureMax": 1, "Damage": "-", "Action": "Dispon\u00edvel", "Price": 10}, "CZ_238_A": {"Name": "Caneca", "Quantity": 2, "Height": 10, "Width": 12, "Depth": 9, "PictureMin": 1, "PictureMax": 1, "Damage": "-", "Action": "Dispon\u00edvel", "Price": 25}, "CZ_238_B": {"Name": "Caneca", "Quantity": 10, "Height": 10, "Width": 12, "Depth": 9, "PictureMin": 2, "PictureMax": 2, "Damage": "-", "Action": "Dispon\u00edvel", "Price": 50}, "CZ_239_A": {"Name": "X\u00edcara", "Quantity": 1, "Height": 8, "Width": 15, "Depth": 15, "PictureMin": 1, "PictureMax": 2, "Damage": "-", "Action": "Dispon\u00edvel", "Price": 75}, "CZ_239_B": {"Name": "X\u00edcara", "Quantity": 1, "Height": 7, "Width": 11, "Depth": 11, "PictureMin": 3, "PictureMax": 3, "Damage": "-", "Action": "Dispon\u00edvel", "Price": 50}, "CZ_239_C": {"Name": "X\u00edcara", "Quantity": 1, "Height": 7, "Width": 12, "Depth": 12, "PictureMin": 4, "PictureMax": 4, "Damage": "-", "Action": "Dispon\u00edvel", "Price": 25}, "CZ_239_D": {"Name": "X\u00edcara", "Quantity": 1, "Height": 8, "Width": 15, "Depth": 15, "PictureMin": 5, "PictureMax": 5, "Damage": "-", "Action": "Dispon\u00edvel", "Price": 25}, "CZ_239_E": {"Name": "X\u00edcara", "Quantity": 1, "Height": 6, "Width": 6, "Depth": 6, "PictureMin": 6, "PictureMax": 6, "Damage": "-", "Action": "Dispon\u00edvel", "Price": 25}, "CZ_239_F": {"Name": "X\u00edcara", "Quantity": 1, "Height": 8, "Width": 6, "Depth": 6, "PictureMin": 7, "PictureMax": 7, "Damage": "-", "Action": "Dispon\u00edvel", "Price": 25}, "CZ_240": {"Name": "Bul\u00ea e leiteira", "Quantity": 1, "Height": 15, "Width": 24, "Depth": 14, "PictureMin": 1, "PictureMax": 1, "Damage": "-", "Action": "Dispon\u00edvel", "Price": 50}, "CZ_241_A": {"Name": "Porta-ovo", "Quantity": 1, "Height": 6, "Width": 5, "Depth": 5, "PictureMin": 1, "PictureMax": 1, "Damage": "-", "Action": "Dispon\u00edvel", "Price": 25}, "CZ_241_B": {"Name": "Porta-ovo", "Quantity": 1, "Height": 6, "Width": 5, "Depth": 5, "PictureMin": 2, "PictureMax": 2, "Damage": "-", "Action": "Dispon\u00edvel", "Price": 25}, "CZ_241_C": {"Name": "Porta-ovo", "Quantity": 1, "Height": 7, "Width": 5, "Depth": 5, "PictureMin": 3, "PictureMax": 3, "Damage": "-", "Action": "Dispon\u00edvel", "Price": 10}, "CZ_242": {"Name": "Jarra", "Quantity": "2", "Height": 25, "Width": 9, "Depth": 12, "PictureMin": 1, "PictureMax": 1, "Damage": "-", "Action": "Dispon\u00edvel", "Price": 0}, "CZ_243_A": {"Name": "Suporte para bolo", "Quantity": 1, "Height": 21, "Width": 30, "Depth": 30, "PictureMin": 1, "PictureMax": 2, "Damage": "-", "Action": "Dispon\u00edvel", "Price": 25}, "CZ_243_B": {"Name": "Suporte para bolo", "Quantity": 1, "Height": 10, "Width": 27, "Depth": 27, "PictureMin": 3, "PictureMax": 4, "Damage": "-", "Action": "Dispon\u00edvel", "Price": 10}, "CZ_243_C": {"Name": "Suporte para bolo", "Quantity": 1, "Height": 14, "Width": 22, "Depth": 22, "PictureMin": 5, "PictureMax": 5, "Damage": "-", "Action": "Dispon\u00edvel", "Price": 10}, "CZ_244_A": {"Name": "Bandeja de doces", "Quantity": 1, "Height": 3, "Width": 33, "Depth": 18, "PictureMin": 1, "PictureMax": 1, "Damage": "-", "Action": "Dispon\u00edvel", "Price": 10}, "CZ_244_B": {"Name": "Bandeja de doces", "Quantity": 1, "Height": 22, "Width": 27, "Depth": 27, "PictureMin": 2, "PictureMax": 2, "Damage": "-", "Action": "Dispon\u00edvel", "Price": 10}, "CZ_244_C": {"Name": "Bandeja de doces", "Quantity": 1, "Height": 29, "Width": 19, "Depth": 19, "PictureMin": 3, "PictureMax": 3, "Damage": "-", "Action": "Dispon\u00edvel", "Price": 10}, "CZ_245": {"Name": "Raclete", "Quantity": 1, "Height": 35, "Width": 35, "Depth": 15, "PictureMin": 1, "PictureMax": 3, "Damage": "Pe\u00e7a derretida e T-fal manchado", "Action": "Dispon\u00edvel", "Price": 75}, "CZ_246": {"Name": "Placa de identifica\u00e7\u00e3o de comida", "Quantity": "5", "Height": 16, "Width": 7, "Depth": 4, "PictureMin": 1, "PictureMax": 1, "Damage": "-", "Action": "Dispon\u00edvel", "Price": 0}, "CZ_247": {"Name": "Panela el\u00e9trica", "Quantity": 1, "Height": 25, "Width": 35, "Depth": 30, "PictureMin": 1, "PictureMax": 2, "Damage": "-", "Action": "Dispon\u00edvel", "Price": 75}, "CZ_248": {"Name": "Espremedor de frutas el\u00e9trico", "Quantity": 1, "Height": 20, "Width": 25, "Depth": 20, "PictureMin": 1, "PictureMax": 2, "Damage": "-", "Action": "Dispon\u00edvel", "Price": 50}, "CZ_249": {"Name": "Bandeja de madeira", "Quantity": 1, "Height": 8, "Width": 44, "Depth": 30, "PictureMin": 1, "PictureMax": 2, "Damage": "-", "Action": "Reservado", "Price": 60}, "CZ_250": {"Name": "Balan\u00e7a de alimentos", "Quantity": 1, "Height": 10, "Width": 18, "Depth": 21, "PictureMin": 1, "PictureMax": 1, "Damage": "Sem pilha", "Action": "Dispon\u00edvel", "Price": 25}, "CZ_251_A": {"Name": "Panela", "Quantity": 1, "Height": 13, "Width": 24, "Depth": 22, "PictureMin": 1, "PictureMax": 2, "Damage": "-", "Action": "Dispon\u00edvel", "Price": 25}, "CZ_251_B": {"Name": "Panela", "Quantity": 1, "Height": 18, "Width": 37, "Depth": 25, "PictureMin": 3, "PictureMax": 3, "Damage": "-", "Action": "Dispon\u00edvel", "Price": 50}, "CZ_252": {"Name": "Aparelho de fondue", "Quantity": 1, "Height": 35, "Width": 35, "Depth": 15, "PictureMin": 1, "PictureMax": 3, "Damage": "-", "Action": "Reservado", "Price": 50}, "CZ_253": {"Name": "Aparelho de waffle", "Quantity": 1, "Height": 12, "Width": 20, "Depth": 25, "PictureMin": 1, "PictureMax": 2, "Damage": "-", "Action": "Dispon\u00edvel", "Price": 50}, "CZ_254": {"Name": "George Foreman", "Quantity": 1, "Height": 15, "Width": 50, "Depth": 35, "PictureMin": 1, "PictureMax": 2, "Damage": "T-fal manchado", "Action": "Dispon\u00edvel", "Price": 50}, "CZ_255": {"Name": "Centr\u00edfuga", "Quantity": 1, "Height": 35, "Width": 25, "Depth": 20, "PictureMin": 1, "PictureMax": 3, "Damage": "-", "Action": "Dispon\u00edvel", "Price": 50}, "CZ_256_A": {"Name": "Copo de \u00e1gua para crian\u00e7a ", "Quantity": "n", "Height": 11, "Width": 13, "Depth": 8, "PictureMin": 1, "PictureMax": 1, "Damage": "-", "Action": "Dispon\u00edvel", "Price": 0}, "CZ_256_B": {"Name": "Copo de \u00e1gua para crian\u00e7a ", "Quantity": "n", "Height": 14, "Width": 12, "Depth": 8, "PictureMin": 2, "PictureMax": 2, "Damage": "-", "Action": "Dispon\u00edvel", "Price": 0}, "CZ_257": {"Name": "Saladeira", "Quantity": 1, "Height": 17, "Width": 27, "Depth": 27, "PictureMin": 1, "PictureMax": 2, "Damage": "-", "Action": "Dispon\u00edvel", "Price": 50}, "CZ_258": {"Name": "Sopeira", "Quantity": 1, "Height": 17, "Width": 30, "Depth": 22, "PictureMin": 1, "PictureMax": 2, "Damage": "-", "Action": "Dispon\u00edvel", "Price": 25}, "CZ_259": {"Name": "Rechaud", "Quantity": 1, "Height": 12, "Width": 34, "Depth": 18, "PictureMin": 1, "PictureMax": 2, "Damage": "-", "Action": "Dispon\u00edvel", "Price": 50}, "CZ_300_A": {"Name": "Forma de silicone para bolo", "Quantity": 1, "Height": 4, "Width": 25, "Depth": 17, "PictureMin": 1, "PictureMax": 1, "Damage": "-", "Action": "Dispon\u00edvel", "Price": 10}, "CZ_300_B": {"Name": "Forma de silicone para bolo", "Quantity": 1, "Height": 5, "Width": 26, "Depth": 26, "PictureMin": 2, "PictureMax": 2, "Damage": "-", "Action": "Dispon\u00edvel", "Price": 10}, "CZ_300_C": {"Name": "Forma de silicone para bolo", "Quantity": 1, "Height": 3, "Width": 30, "Depth": 30, "PictureMin": 3, "PictureMax": 3, "Damage": "-", "Action": "Dispon\u00edvel", "Price": 10}, "CZ_260_A": {"Name": "Forma de bolo", "Quantity": 1, "Height": 7, "Width": 28, "Depth": 23, "PictureMin": 1, "PictureMax": 1, "Damage": "-", "Action": "Dispon\u00edvel", "Price": 10}, "CZ_260_B": {"Name": "Forma de bolo", "Quantity": 1, "Height": 7, "Width": 22, "Depth": 22, "PictureMin": 2, "PictureMax": 3, "Damage": "-", "Action": "Dispon\u00edvel", "Price": 10}, "CZ_262": {"Name": "Jarra de leite", "Quantity": "2", "Height": 10, "Width": 12, "Depth": 7, "PictureMin": 1, "PictureMax": 1, "Damage": "-", "Action": "Dispon\u00edvel", "Price": 10}, "CZ_263_A": {"Name": "Molheira", "Quantity": 1, "Height": 14, "Width": 8, "Depth": 8, "PictureMin": 1, "PictureMax": 1, "Damage": "-", "Action": "Dispon\u00edvel", "Price": 25}, "CZ_263_B": {"Name": "Molheira", "Quantity": 1, "Height": 6, "Width": 13, "Depth": 8, "PictureMin": 2, "PictureMax": 2, "Damage": "-", "Action": "Dispon\u00edvel", "Price": 10}, "CZ_264_A": {"Name": "Livro de receita", "Quantity": "n", "Height": "-", "Width": "-", "Depth": "-", "PictureMin": 1, "PictureMax": 1, "Damage": "-", "Action": "Dispon\u00edvel", "Price": 0}, "CZ_264_B": {"Name": "Livro de receita", "Quantity": "n", "Height": "-", "Width": "-", "Depth": "-", "PictureMin": 2, "PictureMax": 2, "Damage": "-", "Action": "Dispon\u00edvel", "Price": 0}, "CZ_264_C": {"Name": "Livro de receita", "Quantity": "n", "Height": "-", "Width": "-", "Depth": "-", "PictureMin": 3, "PictureMax": 3, "Damage": "-", "Action": "Dispon\u00edvel", "Price": 0}, "CZ_264_D": {"Name": "Livro de receita", "Quantity": "n", "Height": "-", "Width": "-", "Depth": "-", "PictureMin": 4, "PictureMax": 4, "Damage": "-", "Action": "Dispon\u00edvel", "Price": 0}, "CZ_265": {"Name": "Mixer", "Quantity": 1, "Height": 40, "Width": 12, "Depth": 12, "PictureMin": 1, "PictureMax": 2, "Damage": "Bot\u00e3o rasgado", "Action": "Dispon\u00edvel", "Price": 0}, "CZ_266": {"Name": "Batedeira", "Quantity": 1, "Height": 35, "Width": 40, "Depth": 25, "PictureMin": 1, "PictureMax": 3, "Damage": "-", "Action": "Dispon\u00edvel", "Price": 300}, "CZ_267": {"Name": "Liquidificador", "Quantity": 1, "Height": 40, "Width": 20, "Depth": 20, "PictureMin": 1, "PictureMax": 3, "Damage": "Bico quebrado", "Action": "Reservado", "Price": 75}, "CZ_268": {"Name": "Baleiro", "Quantity": "2", "Height": 21, "Width": 16, "Depth": 16, "PictureMin": 1, "PictureMax": 1, "Damage": "-", "Action": "Dispon\u00edvel", "Price": 10}, "CZ_269": {"Name": "Porta-rolha", "Quantity": 1, "Height": 49, "Width": 14, "Depth": 14, "PictureMin": 1, "PictureMax": 1, "Damage": "-", "Action": "Dispon\u00edvel", "Price": 10}, "CZ_298": {"Name": "Pote de mantimentos", "Quantity": "n", "Height": 21, "Width": 12, "Depth": 12, "PictureMin": 1, "PictureMax": 1, "Damage": "-", "Action": "Dispon\u00edvel", "Price": 25}, "CZ_271": {"Name": "Vaso de madeira quadrado", "Quantity": 1, "Height": 45, "Width": 35, "Depth": 35, "PictureMin": 1, "PictureMax": 3, "Damage": "-", "Action": "Dispon\u00edvel", "Price": 50}, "CZ_272": {"Name": "Carrinho de empurrar crian\u00e7as", "Quantity": 1, "Height": 70, "Width": 70, "Depth": 45, "PictureMin": 1, "PictureMax": 2, "Damage": "-", "Action": "Vendido", "Price": 230}, "CZ_273": {"Name": "Caixa de pl\u00e1stico para recicl\u00e1veis", "Quantity": 1, "Height": 28, "Width": 53, "Depth": 37, "PictureMin": 1, "PictureMax": 1, "Damage": "-", "Action": "Dispon\u00edvel", "Price": 0}}}, "lv": {"RoomName": "Lavanderia", "Item": {"LD_274": {"Name": "Caixa organizadora", "Quantity": "2", "Height": 16, "Width": 38, "Depth": 29, "PictureMin": 1, "PictureMax": 2, "Damage": "-", "Action": "Dispon\u00edvel", "Price": 0}, "LD_275": {"Name": "Aspirador de p\u00f3", "Quantity": 1, "Height": 45, "Width": 30, "Depth": 25, "PictureMin": 1, "PictureMax": 2, "Damage": "Pequenos riscos externos", "Action": "Reservado", "Price": 40}, "LD_276": {"Name": "Carrinho de beb\u00ea", "Quantity": "2", "Height": 110, "Width": 95, "Depth": 50, "PictureMin": 1, "PictureMax": 4, "Damage": "Regulagem para apoio das pernas", "Action": "Vendido", "Price": 215}}}, "dp": {"RoomName": "Dispensa", "Item": {"DP_278": {"Name": "T\u00e1bua de passar roupa", "Quantity": 1, "Height": 85, "Width": 130, "Depth": 35, "PictureMin": 1, "PictureMax": 1, "Damage": "Capa manchada", "Action": "Dispon\u00edvel", "Price": 25}, "DP_279": {"Name": "Varal de roupas \u00edntimas", "Quantity": 1, "Height": 20, "Width": 30, "Depth": 20, "PictureMin": 1, "PictureMax": 1, "Damage": "Dois pregadores quebrados", "Action": "Dispon\u00edvel", "Price": 0}, "DP_280": {"Name": "Varal de ch\u00e3o", "Quantity": 1, "Height": 90, "Width": 140, "Depth": 55, "PictureMin": 1, "PictureMax": 1, "Damage": "Pequenas partes enferrujadas", "Action": "Dispon\u00edvel", "Price": 0}, "DP_281": {"Name": "Tapete de beb\u00ea", "Quantity": 1, "Height": 2, "Width": 125, "Depth": 125, "PictureMin": 1, "PictureMax": 2, "Damage": "Pequenos furos de unha de gatos", "Action": "Vendido", "Price": 25}, "DP_282": {"Name": "Escada de alum\u00ednio", "Quantity": 1, "Height": 120, "Width": 40, "Depth": 60, "PictureMin": 1, "PictureMax": 1, "Damage": "Manchas de tinta de parede", "Action": "Reservado", "Price": 30}, "DP_285": {"Name": "Lumin\u00e1ria", "Quantity": 1, "Height": 70, "Width": 10, "Depth": 25, "PictureMin": 1, "PictureMax": 1, "Damage": "Nova (na caixa)", "Action": "Dispon\u00edvel", "Price": 75}, "DP_288_A": {"Name": "Martelo", "Quantity": 1, "Height": "-", "Width": "-", "Depth": "-", "PictureMin": 1, "PictureMax": 1, "Damage": "-", "Action": "Dispon\u00edvel", "Price": 25}, "DP_288_B": {"Name": "Mult\u00edmetro", "Quantity": 1, "Height": "-", "Width": "-", "Depth": "-", "PictureMin": 2, "PictureMax": 2, "Damage": "-", "Action": "Dispon\u00edvel", "Price": 25}, "DP_288_C": {"Name": "Volt\u00edmetro", "Quantity": 1, "Height": "-", "Width": "-", "Depth": "-", "PictureMin": 3, "PictureMax": 3, "Damage": "-", "Action": "Dispon\u00edvel", "Price": 10}, "DP_288_D": {"Name": "Trena", "Quantity": 1, "Height": "-", "Width": "-", "Depth": "-", "PictureMin": 4, "PictureMax": 4, "Damage": "-", "Action": "Dispon\u00edvel", "Price": 10}, "DP_288_E": {"Name": "Serra", "Quantity": 1, "Height": "-", "Width": "-", "Depth": "-", "PictureMin": 5, "PictureMax": 5, "Damage": "-", "Action": "Dispon\u00edvel", "Price": 10}, "DP_288_F": {"Name": "Esquadro", "Quantity": 1, "Height": "-", "Width": "-", "Depth": "-", "PictureMin": 6, "PictureMax": 6, "Damage": "-", "Action": "Dispon\u00edvel", "Price": 25}, "DP_288_H": {"Name": "Rolo de pintar", "Quantity": 1, "Height": "-", "Width": "-", "Depth": "-", "PictureMin": 8, "PictureMax": 8, "Damage": "-", "Action": "Dispon\u00edvel", "Price": 0}, "DP_288_I": {"Name": "Pist\u00e3o", "Quantity": 2, "Height": "-", "Width": "-", "Depth": "-", "PictureMin": 9, "PictureMax": 9, "Damage": "-", "Action": "Dispon\u00edvel", "Price": 0}, "DP_289": {"Name": "Furadeira", "Quantity": 1, "Height": 28, "Width": 30, "Depth": 10, "PictureMin": 1, "PictureMax": 2, "Damage": "-", "Action": "Dispon\u00edvel", "Price": 75}, "DP_290": {"Name": "Parafusadeira el\u00e9trica", "Quantity": 1, "Height": 25, "Width": 35, "Depth": 15, "PictureMin": 1, "PictureMax": 2, "Damage": "-", "Action": "Dispon\u00edvel", "Price": 75}}}, "qg": {"RoomName": "Quarto das gatas", "Item": {"QG_291": {"Name": "Caixa de transporte de gato", "Quantity": "2", "Height": 30, "Width": 30, "Depth": 45, "PictureMin": 1, "PictureMax": 2, "Damage": "-", "Action": "Dispon\u00edvel", "Price": 0}}}, "he": {"RoomName": "Hall de entrada", "Item": {"HE_294_A": {"Name": "Vaso de vidro", "Quantity": 1, "Height": "-", "Width": "-", "Depth": "-", "PictureMin": 1, "PictureMax": 1, "Damage": "-", "Action": "Dispon\u00edvel", "Price": 10}, "HE_294_B": {"Name": "Vaso de vidro", "Quantity": 1, "Height": "-", "Width": "-", "Depth": "-", "PictureMin": 2, "PictureMax": 2, "Damage": "-", "Action": "Dispon\u00edvel", "Price": 10}, "HE_294_C": {"Name": "Vaso de vidro", "Quantity": 1, "Height": "-", "Width": "-", "Depth": "-", "PictureMin": 3, "PictureMax": 3, "Damage": "-", "Action": "Dispon\u00edvel", "Price": 10}, "HE_297": {"Name": "Vaso de coruja", "Quantity": 1, "Height": 20, "Width": 15, "Depth": 15, "PictureMin": 1, "PictureMax": 1, "Damage": "-", "Action": "Dispon\u00edvel", "Price": 25}}}}